MANIFEST.in
README.rst
setup.py
docs/index.rst
pytfmpval/__init__.py
pytfmpval/pytfmpval.py
pytfmpval/pytfmpval_wrap.cxx
pytfmpval/tfmp.py
pytfmpval.egg-info/PKG-INFO
pytfmpval.egg-info/SOURCES.txt
pytfmpval.egg-info/dependency_links.txt
pytfmpval.egg-info/requires.txt
pytfmpval.egg-info/top_level.txt
src/ArgumentException.cpp
src/ArgumentException.h
src/FileException.cpp
src/FileException.h
src/Matrix.cpp
src/Matrix.h
src/ParseException.cpp
src/ParseException.h